decision_tool/__init__.py
decision_tool/__main__.py
decision_tool/_tree_main.py
decision_tool/.ipynb_checkpoints/Untitled-checkpoint.ipynb
decision_tool-1.0.2.dist-info/METADATA
decision_tool-1.0.2.dist-info/WHEEL
decision_tool-1.0.2.dist-info/licenses/LICENSE.txt
decision_tool-1.0.2.dist-info/RECORD
