Metadata-Version: 2.1
Name: decision_tool
Version: 1.0.2
Summary: Decision analysis package with solution and visualization.
Author-email: Ramazan Çevik <ramazancevik119266@gmail.com>
License-File: LICENSE.txt
Classifier: License :: OSI Approved :: Mozilla Public License 2.0 (MPL 2.0)
Classifier: Operating System :: OS Independent
Classifier: Programming Language :: Python :: 3
Classifier: Topic :: Scientific/Engineering
Requires-Python: >=3.6
Requires-Dist: plotly
Requires-Dist: scipy
